fire2a/__init__.py
fire2a/_version.py
fire2a/adjacency.py
fire2a/agglomerative_clustering.py
fire2a/c2f_lookup_table_colors.py
fire2a/cell2fire.py
fire2a/clustering.py
fire2a/downstream_protection_value.py
fire2a/knapsack.py
fire2a/meteo.py
fire2a/processing_utils.py
fire2a/treatmentpreproccessing.py
fire2a/utils.py
fire2a/weathers.py
fire2a/DB_DMC/Adolfo Matthei.csv
fire2a/DB_DMC/Aerodromo Curacavi.csv
fire2a/DB_DMC/Aerodromo Gral Bernardo Ohiggins.csv
fire2a/DB_DMC/Aerodromo Maquehue.csv
fire2a/DB_DMC/Aerodromo Rodelillo.csv
fire2a/DB_DMC/Aerodromo Santo Domingo.csv
fire2a/DB_DMC/Aerodromo Torquemada.csv
fire2a/DB_DMC/Aerodromo de Futaleufu.csv
fire2a/DB_DMC/Aerodromo de Quellon.csv
fire2a/DB_DMC/Aeropuerto Araucania.csv
fire2a/DB_DMC/Aeropuerto El Tepual.csv
fire2a/DB_DMC/Aeropuerto Pichoy.csv
fire2a/DB_DMC/Carriel Sur.csv
fire2a/DB_DMC/Catapilco.csv
fire2a/DB_DMC/Cerro San Francisco.csv
fire2a/DB_DMC/Corral.csv
fire2a/DB_DMC/El Cardal.csv
fire2a/DB_DMC/Escuela Mirasol.csv
fire2a/DB_DMC/Estaciones.csv
fire2a/DB_DMC/Husares.csv
fire2a/DB_DMC/Lago Verde.csv
fire2a/DB_DMC/Las Lomas.csv
fire2a/DB_DMC/Liceo Agricola El Huerton.csv
fire2a/DB_DMC/Nueva Chaiten.csv
fire2a/DB_DMC/Palermo.csv
fire2a/DB_DMC/Panguipulli.csv
fire2a/DB_DMC/Pudahuel.csv
fire2a/DB_DMC/Puerto Varas.csv
fire2a/DB_DMC/Quilacahuin.csv
fire2a/DB_DMC/Quinta Normal.csv
fire2a/DB_DMC/Regimiento Victoria.csv
fire2a/DB_DMC/Rucatayo.csv
fire2a/DB_DMC/Santa Carla.csv
fire2a/DB_DMC/Termas de Chillan.csv
fire2a/DB_DMC/Villarrica.csv
fire2a/raster/__init__.py
fire2a/raster/gdal_calc_norm.py
fire2a/raster/gdal_calc_sum.py
fire2a/raster/raster.py
fire2a_lib-0.3.12.dist-info/licenses/LICENSE.txt
fire2a_lib-0.3.12.dist-info/METADATA
fire2a_lib-0.3.12.dist-info/WHEEL
fire2a_lib-0.3.12.dist-info/entry_points.txt
fire2a_lib-0.3.12.dist-info/top_level.txt
fire2a_lib-0.3.12.dist-info/RECORD
