Metadata-Version: 2.4
Name: fire2a-lib
Version: 0.3.12
Summary: Algorithms and tools python package for Forest Fire Research, Management and Analytics
Author-email: Fernando Badilla <fbadilla@ing.uchile.cl>
License-Expression: GPL-3.0-or-later
Project-URL: homepage, https://www.fire2a.com
Project-URL: documentation, https://fire2a.github.io/fire2a-lib
Project-URL: repository, https://github.com/fire2a/fire2a-lib
Keywords: fire,wildfires,forest fires,fire management,fire analytics,fire research,fire modeling
Classifier: Programming Language :: Python :: 3
Requires-Python: >=3.9
License-File: LICENSE.txt
Requires-Dist: matplotlib
Requires-Dist: networkx>=2.7
Requires-Dist: numpy<2; python_version < "3.11"
Requires-Dist: numpy; python_version >= "3.11"
Requires-Dist: pandas
Requires-Dist: pyomo
Requires-Dist: scikit-learn
Requires-Dist: scipy
Requires-Dist: toml
Dynamic: license-file
